{"stats":{"minecraft:custom":{"minecraft:inspect_dropper":350,"minecraft:inspect_hopper":24,"minecraft:tune_noteblock":676,"minecraft:leave_game":45,"minecraft:time_since_death":127017,"minecraft:time_since_rest":127068,"minecraft:sprint_one_cm":32792,"minecraft:damage_taken":240,"minecraft:walk_one_cm":256390,"minecraft:drop":15,"minecraft:fly_one_cm":13169313,"minecraft:crouch_one_cm":4547,"minecraft:play_time":2452498,"minecraft:deaths":1,"minecraft:sneak_time":116992,"minecraft:walk_under_water_one_cm":9835,"minecraft:interact_with_lectern":178,"minecraft:jump":780,"minecraft:walk_on_water_one_cm":1874,"minecraft:total_world_time":32695570},"minecraft:dropped":{"minecraft:dragon_head":2,"minecraft:wither_skeleton_skull":1,"minecraft:blue_concrete":1,"minecraft:stick":5,"minecraft:dropper":1,"minecraft:white_concrete":4,"minecraft:redstone_block":1},"minecraft:picked_up":{"minecraft:redstone_block":288,"minecraft:repeater":53,"minecraft:iron_door":4,"minecraft:yellow_wool":239,"minecraft:dragon_head":2,"minecraft:golden_sword":8,"minecraft:blue_concrete":1,"minecraft:wither_skeleton_skull":1,"minecraft:sticky_piston":6,"minecraft:magenta_wool":310,"minecraft:activator_rail":24,"minecraft:comparator":3,"minecraft:redstone_torch":4,"minecraft:powered_rail":148,"minecraft:scaffolding":1,"minecraft:stick":3,"minecraft:dropper":1,"minecraft:target":64,"minecraft:cake":3,"minecraft:stone_button":9,"minecraft:redstone":13,"minecraft:orange_wool":200,"minecraft:light_blue_wool":102,"minecraft:lever":3,"minecraft:writable_book":16,"minecraft:white_concrete":325,"minecraft:white_wool":128},"minecraft:used":{"minecraft:water_bucket":12,"minecraft:writable_book":6,"minecraft:dropper":78,"minecraft:orange_concrete":56,"minecraft:red_stained_glass":3,"minecraft:red_concrete":53,"minecraft:redstone":212,"minecraft:powered_rail":584,"minecraft:lime_wool":2,"minecraft:ender_pearl":73,"minecraft:composter":2,"minecraft:brown_concrete":25,"minecraft:redstone_block":136,"minecraft:magenta_stained_glass":3,"minecraft:waxed_copper_block":3,"minecraft:white_wool":46,"minecraft:orange_stained_glass":3,"minecraft:pink_concrete":29,"minecraft:diamond_block":66,"minecraft:target":1,"minecraft:comparator":225,"minecraft:light_blue_concrete":61,"minecraft:hopper":39,"minecraft:blue_stained_glass":3,"minecraft:light_blue_wool":23,"minecraft:birch_sign":37,"minecraft:orange_wool":28,"minecraft:yellow_concrete":56,"minecraft:note_block":86,"minecraft:gray_concrete":17,"minecraft:cyan_wool":6,"minecraft:blue_concrete":19,"minecraft:cake":2,"minecraft:obsidian":2,"minecraft:cyan_stained_glass":3,"minecraft:redstone_torch":7,"minecraft:purple_stained_glass":3,"minecraft:sticky_piston":95,"minecraft:piston":114,"minecraft:black_wool":2,"minecraft:netherite_block":42,"minecraft:lever":17,"minecraft:honey_block":4,"minecraft:black_concrete":17,"minecraft:activator_rail":46,"minecraft:daylight_detector":38,"minecraft:command_block":219,"minecraft:red_wool":24,"minecraft:yellow_stained_glass":3,"minecraft:iron_block":26,"minecraft:brown_stained_glass":3,"minecraft:brown_wool":2,"minecraft:barrier":4,"minecraft:slime_block":13,"minecraft:stone_button":12,"minecraft:lectern":2,"minecraft:magenta_concrete":54,"minecraft:cyan_concrete":28,"minecraft:spruce_trapdoor":17,"minecraft:iron_door":3,"minecraft:pink_wool":2,"minecraft:yellow_wool":26,"minecraft:bedrock":9,"minecraft:repeater":873,"minecraft:purple_concrete":27,"minecraft:redstone_lamp":83,"minecraft:lime_concrete":54,"minecraft:black_stained_glass":3,"minecraft:magenta_wool":29,"minecraft:scaffolding":2,"minecraft:emerald_block":40,"minecraft:iron_trapdoor":3,"minecraft:lime_stained_glass":3,"minecraft:white_stained_glass":774,"minecraft:chain_command_block":6,"minecraft:pink_stained_glass":3,"minecraft:gold_block":33,"minecraft:repeating_command_block":4,"minecraft:white_concrete":865,"minecraft:gray_wool":2,"minecraft:observer":525,"minecraft:purple_wool":2,"minecraft:gray_stained_glass":3}},"DataVersion":2975}